ws/mailcheck/__init__.py
ws/mailcheck/main.py
ws.mailcheck-1.0.5.dist-info/METADATA
ws.mailcheck-1.0.5.dist-info/WHEEL
ws.mailcheck-1.0.5.dist-info/entry_points.txt
ws.mailcheck-1.0.5.dist-info/RECORD
