Metadata-Version: 2.1
Name: ws.mailcheck
Version: 1.0.5
Summary: Sends a test email via SMTP, and checks that it was received via IMAP
Project-URL: Repository, https://github.com/wosc/mailcheck
Author-email: Wolfgang Schnerring <wosc@wosc.de>
License:  BSD-3-Clause
Requires-Python: >=3.7
Provides-Extra: test
Requires-Dist: pytest; extra == 'test'
Requires-Dist: pytest-cov; extra == 'test'
